LICENSE.txt
MANIFEST.in
README.md
README.srt
setup.cfg
setup.py
bin/longtang
longtang/__init__.py
longtang.egg-info/PKG-INFO
longtang.egg-info/SOURCES.txt
longtang.egg-info/dependency_links.txt
longtang.egg-info/requires.txt
longtang.egg-info/top_level.txt
longtang/actors/__init__.py
longtang/actors/actors.py
longtang/actors/actorstestutils.py
longtang/actors/domain.py
longtang/actors/messages.py
longtang/actors/filesystem/__init__.py
longtang/actors/filesystem/domain.py
longtang/actors/filesystem/filemanager.py
longtang/actors/filesystem/foldermanager.py
longtang/actors/filesystem/messages.py
longtang/actors/filesystem/test/__init__.py
longtang/actors/filesystem/test/test_filemanager.py
longtang/actors/filesystem/test/test_foldermanager.py
longtang/actors/inbound/__init__.py
longtang/actors/inbound/filepoller.py
longtang/actors/inbound/messages.py
longtang/actors/inbound/inflate/__init__.py
longtang/actors/inbound/inflate/filepump.py
longtang/actors/inbound/inflate/messages.py
longtang/actors/inbound/inflate/pumpingclerk.py
longtang/actors/inbound/inflate/strategies/__init__.py
longtang/actors/inbound/inflate/strategies/base.py
longtang/actors/inbound/inflate/strategies/rarpumping.py
longtang/actors/inbound/inflate/strategies/registry.py
longtang/actors/inbound/inflate/strategies/sevenzpumping.py
longtang/actors/inbound/inflate/strategies/zippumping.py
longtang/actors/inbound/inflate/test/__init__.py
longtang/actors/inbound/inflate/test/test_filepump.py
longtang/actors/inbound/test/__init__.py
longtang/actors/inbound/test/test_filepoller.py
longtang/actors/logger/__init__.py
longtang/actors/logger/factory.py
longtang/actors/logger/logger.py
longtang/actors/logger/messages.py
longtang/actors/logger/test/__init__.py
longtang/actors/logger/test/test_logger.py
longtang/actors/media/__init__.py
longtang/actors/media/id3tag/__init__.py
longtang/actors/media/id3tag/domain.py
longtang/actors/media/id3tag/id3tagchecker.py
longtang/actors/media/id3tag/id3tagwriter.py
longtang/actors/media/id3tag/medianame.py
longtang/actors/media/id3tag/messages.py
longtang/actors/media/id3tag/test/__init__.py
