Metadata-Version: 1.1
Name: longtang
Version: 1.2.0
Summary: Music library organizer and id3 tag manager
Home-page: https://bitbucket.org/gszeliga/longtang
Author: Guillermo Szeliga
Author-email: gszeliga@gmail.com
License: MIT
Keywords: audio mp3 id3 tag actors music collection musicbrainz
Platform: ALL
Classifier: Development Status :: 6 - Mature
Classifier: Environment :: Console
Classifier: Intended Audience :: End Users/Desktop
Classifier: Operating System :: Unix
Classifier: Programming Language :: Python :: 2.7
Classifier: Topic :: Multimedia :: Sound/Audio
Classifier: Topic :: Multimedia :: Sound/Audio :: Conversion
Classifier: Topic :: Multimedia :: Sound/Audio :: Editors
Classifier: Topic :: Software Development :: Libraries :: Python Modules
Classifier: Topic :: Utilities
